RC_lib/Funciones.py
RC_lib/__init__.py
encontrar_bordes-0.0.13.dist-info/METADATA
encontrar_bordes-0.0.13.dist-info/WHEEL
encontrar_bordes-0.0.13.dist-info/top_level.txt
encontrar_bordes-0.0.13.dist-info/RECORD
