Metadata-Version: 2.1
Name: encontrar-bordes
Version: 0.0.13
Summary: Librería para extraer los contornos de una imagen, mostrarla y graficarla sobre la imagen original
Home-page: https://github.com/Ezequiel2003/UNSL---Proyecto-DSP2---Cordoba-Romero
Author: Paul Andres Romero Coronado <paulssj14@gmail.com>Pablo Ezequiel Cordoba <ezequielcordoba39@gmail.com>
License: UNSL
Requires-Dist: opencv-python
Requires-Dist: numpy
